{
  "pdfId": "C4.67",
  "sourceFile": "C4.67 WriteUniquePtlStash.md",
  "title": "WriteUniquePtlStash",
  "chiVersion": "IHI0050H",
  "pageStart": null,
  "pageEnd": null,
  "mainTopics": [
    "WriteUniquePtlStash"
  ],
  "contentTypes": {
    "hasChunks": false,
    "hasObjects": false,
    "hasRules": false,
    "hasFlows": false,
    "hasVerificationPoints": false,
    "hasTables": false,
    "hasFigures": false
  },
  "dependsOn": [],
  "relatedSections": [
    "Request types",
    "Write transaction flows"
  ],
  "processingStatus": {
    "extracted": false,
    "reviewed": false,
    "quality": "empty-source",
    "notes": "Source markdown is empty; only metadata and empty record files were generated."
  },
  "recordStats": {
    "chunks": 0,
    "objects": 0,
    "rules": 0,
    "flows": 0,
    "verification": 0,
    "relations": 0,
    "tables": 0,
    "figures": 0
  }
}
